{"id":"ChIJ6dxGa-XHwoARA2YS0yaI0z8","nationalPhoneNumber":"(213) 389-6140","formattedAddress":"3200 W 8th St, Los Angeles, CA 90005, USA","rating":4.2,"googleMapsUri":"https://maps.google.com/?cid=4599169344806741507","websiteUri":"http://www.hcafes.com/","userRatingCount":499,"displayName":{"text":"H Cafe","languageCode":"en"},"currentOpeningHours":{"openNow":true,"periods":[{"open":{"day":0,"hour":9,"minute":0,"date":{"year":2023,"month":12,"day":24}},"close":{"day":0,"hour":16,"minute":0,"date":{"year":2023,"month":12,"day":24}}},{"open":{"day":1,"hour":9,"minute":0,"date":{"year":2023,"month":12,"day":25}},"close":{"day":1,"hour":16,"minute":0,"date":{"year":2023,"month":12,"day":25}}},{"open":{"day":2,"hour":9,"minute":0,"date":{"year":2023,"month":12,"day":26}},"close":{"day":2,"hour":16,"minute":0,"date":{"year":2023,"month":12,"day":26}}},{"open":{"day":3,"hour":9,"minute":0,"date":{"year":2023,"month":12,"day":20}},"close":{"day":3,"hour":16,"minute":0,"date":{"year":2023,"month":12,"day":20}}},{"open":{"day":3,"hour":18,"minute":0,"date":{"year":2023,"month":12,"day":20}},"close":{"day":3,"hour":23,"minute":0,"date":{"year":2023,"month":12,"day":20}}},{"open":{"day":4,"hour":9,"minute":0,"date":{"year":2023,"month":12,"day":21}},"close":{"day":4,"hour":16,"minute":0,"date":{"year":2023,"month":12,"day":21}}},{"open":{"day":4,"hour":18,"minute":0,"date":{"year":2023,"month":12,"day":21}},"close":{"day":4,"hour":23,"minute":0,"date":{"year":2023,"month":12,"day":21}}},{"open":{"day":5,"hour":9,"minute":0,"date":{"year":2023,"month":12,"day":22}},"close":{"day":5,"hour":16,"minute":0,"date":{"year":2023,"month":12,"day":22}}},{"open":{"day":5,"hour":18,"minute":0,"date":{"year":2023,"month":12,"day":22}},"close":{"day":5,"hour":23,"minute":0,"date":{"year":2023,"month":12,"day":22}}},{"open":{"day":6,"hour":9,"minute":0,"date":{"year":2023,"month":12,"day":23}},"close":{"day":6,"hour":16,"minute":0,"date":{"year":2023,"month":12,"day":23}}},{"open":{"day":6,"hour":18,"minute":0,"date":{"year":2023,"month":12,"day":23}},"close":{"day":6,"hour":23,"minute":0,"date":{"year":2023,"month":12,"day":23}}}],"weekdayDescriptions":["Monday: 9:00 AM – 4:00 PM","Tuesday: 9:00 AM – 4:00 PM","Wednesday: 9:00 AM – 4:00 PM, 6:00 – 11:00 PM","Thursday: 9:00 AM – 4:00 PM, 6:00 – 11:00 PM","Friday: 9:00 AM – 4:00 PM, 6:00 – 11:00 PM","Saturday: 9:00 AM – 4:00 PM, 6:00 – 11:00 PM","Sunday: 9:00 AM – 4:00 PM"]},"editorialSummary":{"text":"Casual venue in the H Hotel, spotlighting homestyle fare like sandwiches & pasta, plus cocktails.","languageCode":"en"},"outdoorSeating":true,"parkingOptions":{"freeParkingLot":true,"paidParkingLot":true,"paidStreetParking":true}}